AUTHORS.rst
CONTRIBUTING.rst
HISTORY.rst
LICENSE
MANIFEST.in
README.rst
setup.cfg
setup.py
docs/Makefile
docs/authors.rst
docs/conf.py
docs/contributing.rst
docs/history.rst
docs/index.rst
docs/installation.rst
docs/make.bat
docs/readme.rst
docs/usage.rst
fitnick/__init__.py
fitnick/cli.py
fitnick/main.py
fitnick.egg-info/PKG-INFO
fitnick.egg-info/SOURCES.txt
fitnick.egg-info/dependency_links.txt
fitnick.egg-info/entry_points.txt
fitnick.egg-info/not-zip-safe
fitnick.egg-info/requires.txt
fitnick.egg-info/top_level.txt
fitnick/base/__init__.py
fitnick/base/base.py
fitnick/database/__init__.py
fitnick/database/database.py
fitnick/flask_app/__init__.py
fitnick/flask_app/main.py
fitnick/heart_rate/__init__.py
fitnick/heart_rate/heart_rate.py
fitnick/heart_rate/main.py
fitnick/heart_rate/models.py
tests/__init__.py
tests/test_base.py
tests/test_database.py
tests/test_heart_rate.py